ocr_translate_hugging_face/__init__.py
ocr_translate_hugging_face/plugin/__init__.py
ocr_translate_hugging_face/plugin/seq2seq.py
ocr_translate_hugging_face/plugin/tokenization_small100.py
ocr_translate_hugging_face/plugin/utils.py
ocr_translate_hugging_face/plugin/ved.py
ocr_translate_hugging_face-0.4.0.dist-info/entry_points.txt
ocr_translate_hugging_face-0.4.0.dist-info/licenses/LICENSE.txt
ocr_translate_hugging_face-0.4.0.dist-info/WHEEL
ocr_translate_hugging_face-0.4.0.dist-info/METADATA
ocr_translate_hugging_face-0.4.0.dist-info/RECORD
